terminus/__init__.py
terminus/asciinema_handler.py
terminus/cli.py
terminus/get-asciinema-timestamp.sh
terminus/local_environment.py
terminus/terminus.py
terminus/terminus_json_plain_parser.py
terminus/terminus_xml_plain_parser.py
terminus/tmux_session.py
terminus/templates/terminus-json-plain.txt
terminus/templates/terminus-xml-plain.txt
terminus/templates/timeout.txt
terminus_ai-2.0.4.dist-info/METADATA
terminus_ai-2.0.4.dist-info/WHEEL
terminus_ai-2.0.4.dist-info/entry_points.txt
terminus_ai-2.0.4.dist-info/top_level.txt
terminus_ai-2.0.4.dist-info/RECORD
