Metadata-Version: 2.4
Name: terminus-ai
Version: 2.0.4
Summary: Terminus CLI: An autonomous AI agent for terminal-based task execution
Requires-Python: >=3.12
Requires-Dist: pydantic>=2.11.7
Requires-Dist: litellm>=1.79.0
Requires-Dist: tenacity>=9.1.2
Requires-Dist: jinja2>=3.1.6
Requires-Dist: typer>=0.16.0
Requires-Dist: harbor>=0.1.17
